{"cameraMode":{"drawMode":0,"name":"Shaded","section":"Shading Mode"},"sceneLighting":false,"audioPlay":false,"sceneViewState":{"showFog":true,"showMaterialUpdate":false,"showSkybox":false,"showFlares":true,"showImageEffects":true,"showParticleSystems":true},"in2DMode":false,"pivot":{"x":12.711848258972168,"y":-3.4578394889831545,"z":7.289898872375488},"rotation":{"x":-0.2355077713727951,"y":0.6612574458122253,"z":-0.23116816580295564,"w":-0.673672080039978},"size":4.768163681030273,"orthographic":false}